Verilog/CS120A/lab3/design.sv
// Code your design here
`timescale 1ns / 1ps
module bcd_to_7led_bh (
input wire sw0 , // Switches
input wire sw1 ,
input wire sw2 ,
input wire sw3 ,
output reg a , // LED segments
output reg b ,
output reg c ,
output reg d ,
output reg e ,
output reg f ,
output reg g
 );

// Internal wire
wire [3:0] bundle ;
assign bundle = {sw3,sw2,sw1,sw0 } ;
always @(*) begin

// Setting the segments signals (Initialize all to off/1)
a = 1'b1 ;
b = 1'b1 ;
c = 1'b1 ;
d = 1'b1 ;
e = 1'b1 ;
f = 1'b1 ;
g = 1'b1 ;

case ( bundle )
4'b0000 : begin // 0
a = 1'b0 ;
b = 1'b0 ;
c = 1'b0 ;
d = 1'b0 ;
e = 1'b0 ;
f = 1'b0 ;
g = 1'b1 ; //(Don’t need to explicitly state that g is off here since
 // it is initialized to off already, but it doesn’t hurt)
end

  4'b0001 : begin // 1
a = 1'b1 ;
b = 1'b0 ;
c = 1'b0 ;
d = 1'b1 ;
e = 1'b1 ;
f = 1'b1 ;
 g = 1'b1 ; //(Don’t need to explicitly state that g is off here since
 // it is initialized to off already, but it doesn’t hurt)
end

  4'b0010 : begin // 2
a = 1'b0 ;
b = 1'b0 ;
c = 1'b1 ;
d = 1'b0 ;
e = 1'b0 ;
f = 1'b1 ;
 g = 1'b0 ; //(Don’t need to explicitly state that g is off here since
 // it is initialized to off already, but it doesn’t hurt)
end

  4'b0011 : begin // 3
a = 1'b0 ;
b = 1'b0 ;
c = 1'b0 ;
d = 1'b0 ;
e = 1'b1 ;
f = 1'b1 ;
 g = 1'b0 ; //(Don’t need to explicitly state that g is off here since
 // it is initialized to off already, but it doesn’t hurt)
end

  4'b0100 : begin // 4
a = 1'b1 ;
b = 1'b0 ;
c = 1'b0 ;
d = 1'b1 ;
e = 1'b1 ;
f = 1'b0 ;
 g = 1'b0 ; //(Don’t need to explicitly state that g is off here since
 // it is initialized to off already, but it doesn’t hurt)
end
  4'b0101 : begin // 5
a = 1'b0 ;
b = 1'b1 ;
c = 1'b0 ;
d = 1'b0 ;
e = 1'b1 ;
f = 1'b0 ;
 g = 1'b0 ; //(Don’t need to explicitly state that g is off here since
 // it is initialized to off already, but it doesn’t hurt)
end

  4'b0110 : begin // 6
a = 1'b0 ;
b = 1'b1 ;
c = 1'b0 ;
d = 1'b0 ;
e = 1'b0 ;
f = 1'b0 ;
 g = 1'b0 ; //(Don’t need to explicitly state that g is off here since
 // it is initialized to off already, but it doesn’t hurt)
end

  4'b0111 : begin // 7
a = 1'b0 ;
b = 1'b0 ;
c = 1'b0 ;
d = 1'b1 ;
e = 1'b1 ;
f = 1'b1 ;
 g = 1'b1 ; //(Don’t need to explicitly state that g is off here since
 // it is initialized to off already, but it doesn’t hurt)
end

  4'b1000 : begin // 8
a = 1'b0 ;
b = 1'b0 ;
c = 1'b0 ;
d = 1'b0 ;
e = 1'b0 ;
f = 1'b0 ;
 g = 1'b0 ; //(Don’t need to explicitly state that g is off here since
 // it is initialized to off already, but it doesn’t hurt)
end

  4'b1001 : begin // 0
a = 1'b0 ;
b = 1'b0 ;
c = 1'b0 ;
d = 1'b0 ;
e = 1'b1 ;
f = 1'b0 ;
 g = 1'b0 ; //(Don’t need to explicitly state that g is off here since
 // it is initialized to off already, but it doesn’t hurt)
end
// Your code goes here for the other 8 numbers (1-9)
endcase
end
endmodule

Verilog/CS120A/lab3/testbench.sv
// Code your testbench here
`include "design.sv"
// or browse Examples
`timescale 1ns / 1ps
// http://www.electronics-tutorials.ws/combination/comb_6.html
module bcdtoled_tb;
// Inputs
reg sw0;
reg sw1;
reg sw2;
reg sw3;
// Outputs
wire a;
wire b;
wire c;
wire d;
wire e;
wire f;
wire g;
// Instantiate the Unit Under Test (UUT)
// bcdto7led_st uut (
bcd_to_7led_bh uut (
.sw0(sw0),
.sw1(sw1),
.sw2(sw2),
.sw3(sw3),
.a(a),
.b(b),
.c(c),
.d(d),
.e(e),
.f(f),
.g(g)
);

initial begin
$dumpfile("dump.vcd"); $dumpvars;
// Initialize Inputs
sw3 = 0; sw2 = 0; sw1 = 0; sw0 = 0;
#50;
 $display("TC10 ");
if ( {a,b,c,d,e,f,g} != 7'b0000001 ) $display ("Result is wrong, input:%b, output: %b",{sw3, sw2, sw1, sw0}, {a,b,c,d,e,f,g});;
 // Your test cases go here (9 left)
    sw3 = 0; sw2 = 0; sw1 = 0; sw0 = 1;
  #50;
  if ( {a,b,c,d,e,f,g} != 7'b1001111 ) $display ("Result is wrong, input:%b, output: %b",{sw3, sw2, sw1, sw0}, {a,b,c,d,e,f,g});;
    sw3 = 0; sw2 = 0; sw1 = 1; sw0 = 0;

  #50;
  if ( {a,b,c,d,e,f,g} != 7'b0010010 ) $display ("Result is wrong, input:%b, output: %b",{sw3, sw2, sw1, sw0}, {a,b,c,d,e,f,g});;
    sw3 = 0; sw2 = 0; sw1 = 1; sw0 = 1;

  #50;
  if ( {a,b,c,d,e,f,g} != 7'b0000110 ) $display ("Result is wrong, input:%b, output: %b",{sw3, sw2, sw1, sw0}, {a,b,c,d,e,f,g});;
    sw3 = 0; sw2 = 1; sw1 = 0; sw0 = 0;

  #50;
  if ( {a,b,c,d,e,f,g} != 7'b1001100 ) $display ("Result is wrong, input:%b, output: %b",{sw3, sw2, sw1, sw0}, {a,b,c,d,e,f,g});;
    sw3 = 0; sw2 = 1; sw1 = 0; sw0 = 1;

  #50;
  if ( {a,b,c,d,e,f,g} != 7'b0100100 ) $display ("Result is wrong, input:%b, output: %b",{sw3, sw2, sw1, sw0}, {a,b,c,d,e,f,g});;
    sw3 = 0; sw2 = 1; sw1 = 1; sw0 = 0;

  #50;
  if ( {a,b,c,d,e,f,g} != 7'b0100000 ) $display ("Result is wrong, input:%b, output: %b",{sw3, sw2, sw1, sw0}, {a,b,c,d,e,f,g});;
    sw3 = 0; sw2 = 1; sw1 = 1; sw0 = 1;

  #50;
  if ( {a,b,c,d,e,f,g} != 7'b0001111 ) $display ("Result is wrong, input:%b, output: %b",{sw3, sw2, sw1, sw0}, {a,b,c,d,e,f,g});;
    sw3 = 1; sw2 = 0; sw1 = 0; sw0 = 0;

  #50;
  if ( {a,b,c,d,e,f,g} != 7'b0000000 ) $display ("Result is wrong, input:%b, output: %b",{sw3, sw2, sw1, sw0}, {a,b,c,d,e,f,g});;

    sw3 = 1; sw2 = 0; sw1 = 0; sw0 = 1;
  #50;
  if ( {a,b,c,d,e,f,g} != 7'b0000100 ) $display ("Result is wrong, input:%b, output: %b",{sw3, sw2, sw1, sw0}, {a,b,c,d,e,f,g});

end
endmodule

Verilog/CS120A/lab3/dump.vcd
$date
	Tue Apr 30 13:05:59 2024
$end
$version
	Icarus Verilog
$end
$timescale
	1ps
$end
$scope module bcdtoled_tb $end
$var wire 1 ! g $end
$var wire 1 " f $end
$var wire 1 # e $end
$var wire 1 $ d $end
$var wire 1 % c $end
$var wire 1 & b $end
$var wire 1 ' a $end
$var reg 1 ( sw0 $end
$var reg 1 ) sw1 $end
$var reg 1 * sw2 $end
$var reg 1 + sw3 $end
$scope module uut $end
$var wire 1 ( sw0 $end
$var wire 1 ) sw1 $end
$var wire 1 * sw2 $end
$var wire 1 + sw3 $end
$var wire 4 , bundle [3:0] $end
$var reg 1 ' a $end
$var reg 1 & b $end
$var reg 1 % c $end
$var reg 1 $ d $end
$var reg 1 # e $end
$var reg 1 " f $end
$var reg 1 ! g $end
$upscope $end
$upscope $end
$enddefinitions $end
$comment Show the parameter values. $end
$dumpall
$end
#0
$dumpvars
b0 ,
0+
0*
0)
0(
0'
0&
0%
0$
0#
0"
1!
$end
#50000
1"
1#
1$
0%
0&
1'
b1 ,
1(
#100000
0!
0#
0$
0'
1%
0&
0(
b10 ,
1)
#150000
0%
0!
1#
0$
0&
0'
b11 ,
1(
#200000
0"
0!
1$
0%
0&
1'
0(
0)
b100 ,
1*
#250000
0$
0'
0!
0"
0%
1&
b101 ,
1(
#300000
0#
0!
0"
0$
0%
0'
0(
b110 ,
1)
#350000
0&
1!
1"
1#
1$
0%
0'
b111 ,
1(
#400000
0!
0"
0#
0$
0%
0&
0'
0(
0)
0*
b1000 ,
1+
#450000
0!
0"
1#
0$
0%
0&
0'
b1001 ,
1(
