Verilog/CS120A/lab4/design.sv
module fasystem_bh(
input wire clk,
input wire call_button ,
input wire cancel_button ,
output reg light_state
);
// Internal wire
reg c_state ;
// Combinatorial block
always @(*) begin
    // q = light_state
    // c_state = call
case ({call_button,cancel_button})
2'b00: c_state = light_state ? 'd1 : 'd0 ;
2'b01: c_state = 'd0 ;

// Write the two following states
2'b10: c_state = 'd1;
2'b11: c_state = 'd1;
default : c_state = 'd0 ;
endcase
end
// Sequential block
always @( posedge clk ) begin
    light_state <= c_state ;
end
endmodule

module edgedetector_bh(
input wire clk,
input wire signal,
output reg outedge );

wire slow_clk ;
reg [1:0] c_state ;
reg [1:0] r_state ;
// Define your FSM states
localparam ZERO = 'd0;
localparam CHANGE = 'd1;
localparam ONE = 'd2;
// EECS150 - Digital Design Lecture 17 - Finite State Machines Revisited
// Code for clkdiv module is given below. Create a new Verilog module in the
//same project with the given code.
clkdiv c1(clk, slow_clk );
// Comb. logic.
always @(*) begin
case (r_state)
ZERO : begin
c_state = signal ? CHANGE : ZERO ;
outedge = 'd0 ;
end
CHANGE : begin
    c_state = signal ? ONE : ZERO ;
    outedge = 'd1;
end
ONE : begin
    c_state = signal ? ONE : ZERO ;
    outedge = 'd0;
end
default : begin
c_state = ZERO ;
outedge = 'd0 ;
end
endcase

end
// Seq. logic
always @( posedge slow_clk ) begin
r_state <= c_state ;
end
endmodule

module clkdiv(clk,clk_out);
input clk;
output clk_out;
reg [15:0] COUNT;
initial COUNT = 0;
assign clk_out=COUNT[3];
always @(posedge clk)
begin
COUNT = COUNT + 1;
end
endmodule

Verilog/CS120A/lab4/testbench.sv
// including design file
`include "design.sv"
`timescale 1ns/1ns;

 module fasystemTest;

    //list of input ports..
    reg clk;
    //add other input ports that you will need. For example the following is for
    //flight attendant system.
    reg Call;
    reg Cancel;
    // add the required input ports for the module you are testing.

    //list of output ports..
    wire Light; //add output ports as required to test your module

    //instantiate your module to be tested here and connect ports appropriately
    //your_module_name uut (.port_name_in_module(port_name_in_testbench),...)
    //As an example module instantiation to test flight attendant call system is given below:

    fasystem_bh uut(.call_button(Call), .cancel_button(Cancel), .light_state(Light), .clk(clk));

    always #1 clk=~clk; // this will create a clock signal with fr equency of(1/2ns=500MZ)

    initial begin

        $dumpfile("fasystemOut.vcd");
        $dumpvars;

        clk=0; //this will initialize clk to logic 0 at time 0ns

        //Start giving stimulation to input ports as required to test your module here.
        //A sample stimulus set to test flight attendant call system
        // is given below as an example:

        Call=0; Cancel=0;
        #17;  //wait for appropriate amount of time so that you can see
        //some impact of input to output (i.e all the clocks in your module at least
        //completes one cycle. This includes the slow_clk as well if used. )
        Call=0; Cancel=1;
        #13;
        Call=1; Cancel=0;
        #19;
        Call=1; Cancel=1;
        #33;
        Call=0; Cancel=1;
        #13;
        Call=1; Cancel=1;
        #27;
        Call=0; Cancel=1;
        #29;

        $finish; //this is very important. Otherwise your test will
        //never stop as clock will keep running infinitely according to line 23.

    end
endmodule

module edgedectectorTest;

    //list of input ports..
    reg clk;
    //add other input ports that you will need. For example the following is for
    //flight attendant system.
    reg signal;
    // add the required input ports for the module you are testing.

    //list of output ports..
    wire outedge; //add output ports as required to test your module

    //instantiate your module to be tested here and connect ports appropriately
    //your_module_name uut (.port_name_in_module(port_name_in_testbench),...)
    //As an example module instantiation to test flight attendant call system is given below:

    edgedetector_bh uut(.clk(clk), .signal(signal), .outedge(outedge));

    always #1 clk=~clk; // this will create a clock signal with fr equency of(1/2ns=500MZ)

    initial begin

        $dumpfile("edgeDetectorOut.vcd");
        $dumpvars;

        clk=0; //this will initialize clk to logic 0 at time 0ns

        //Start giving stimulation to input ports as required to test your module here.
        //A sample stimulus set to test flight attendant call system
        // is given below as an example:

        signal = 0;
        #559;

        signal = 1;
        #559;

        signal = 0;
        #559;

        signal = 1;
        #559;

        signal = 0;
        #559;

        signal = 1;
        #559;

        signal = 0;
        #179;

        signal = 1;
        #99;

        signal = 0;
        #559;

        signal = 1;
        #559;

        signal = 0;
        #559;

        $finish; //this is very important. Otherwise your test will
        //never stop as clock will keep running infinitely according to line 23.

    end
endmodule

Verilog/CS120A/lab4/edgeDetectorOut.vcd
$date
	Tue May 14 14:07:04 2024
$end
$version
	Icarus Verilog
$end
$timescale
	1ns
$end
$scope module edgedectectorTest $end
$var wire 1 ! outedge $end
$var reg 1 " clk $end
$var reg 1 # signal $end
$scope module uut $end
$var wire 1 " clk $end
$var wire 1 # signal $end
$var wire 1 $ slow_clk $end
$var parameter 32 % CHANGE $end
$var parameter 32 & ONE $end
$var parameter 32 ' ZERO $end
$var reg 2 ( c_state [1:0] $end
$var reg 1 ! outedge $end
$var reg 2 ) r_state [1:0] $end
$scope module c1 $end
$var wire 1 " clk $end
$var wire 1 $ clk_out $end
$var reg 16 * COUNT [15:0] $end
$upscope $end
$upscope $end
$upscope $end
$scope module fasystemTest $end
$var wire 1 + Light $end
$var reg 1 , Call $end
$var reg 1 - Cancel $end
$var reg 1 . clk $end
$scope module uut $end
$var wire 1 , call_button $end
$var wire 1 - cancel_button $end
$var wire 1 . clk $end
$var reg 1 / c_state $end
$var reg 1 + light_state $end
$upscope $end
$upscope $end
$scope module edgedectectorTest $end
$scope module uut $end
$scope module c1 $end
$upscope $end
$upscope $end
$upscope $end
$scope module fasystemTest $end
$scope module uut $end
$upscope $end
$upscope $end
$enddefinitions $end
$comment Show the parameter values. $end
$dumpall
b0 '
b10 &
b1 %
$end
#0
$dumpvars
x/
0.
0-
0,
x+
b0 *
bx )
b0 (
0$
0#
0"
0!
$end
#1
b1 *
1.
1"
#2
0.
0"
#3
b10 *
1.
1"
#4
0.
0"
#5
b11 *
1.
1"
#6
0.
0"
#7
b100 *
1.
1"
#8
0.
0"
#9
b101 *
1.
1"
#10
0.
0"
#11
b110 *
1.
1"
#12
0.
0"
#13
b111 *
1.
1"
#14
0.
0"
#15
b0 )
1$
b1000 *
1.
1"
#16
0.
0"
#17
0+
b1001 *
0/
1.
1"
1-
#18
0.
0"
#19
b1010 *
1.
1"
#20
0.
0"
#21
b1011 *
1.
1"
#22
0.
0"
#23
b1100 *
1.
1"
#24
0.
0"
#25
b1101 *
1.
1"
#26
0.
0"
#27
b1110 *
1.
1"
#28
0.
0"
#29
b1111 *
1.
1"
#30
1/
0.
0"
0-
1,
#31
1+
0$
b10000 *
1.
1"
#32
0.
0"
#33
b10001 *
1.
1"
#34
0.
0"
#35
b10010 *
1.
1"
#36
0.
0"
#37
b10011 *
1.
1"
#38
0.
0"
#39
b10100 *
1.
1"
#40
0.
0"
#41
b10101 *
1.
1"
#42
0.
0"
#43
b10110 *
1.
1"
#44
0.
0"
#45
b10111 *
1.
1"
#46
0.
0"
#47
1$
b11000 *
1.
1"
#48
0.
0"
#49
b11001 *
1.
1"
1-
#50
0.
0"
#51
b11010 *
1.
1"
#52
0.
0"
#53
b11011 *
1.
1"
#54
0.
0"
#55
b11100 *
1.
1"
#56
0.
0"
#57
b11101 *
1.
1"
#58
0.
0"
#59
b11110 *
1.
1"
#60
0.
0"
#61
b11111 *
1.
1"
#62
0.
0"
#63
0$
b100000 *
1.
1"
#64
0.
0"
#65
b100001 *
1.
1"
#66
0.
0"
#67
b100010 *
1.
1"
#68
0.
0"
#69
b100011 *
1.
1"
#70
0.
0"
#71
b100100 *
1.
1"
#72
0.
0"
#73
b100101 *
1.
1"
#74
0.
0"
#75
b100110 *
1.
1"
#76
0.
0"
#77
b100111 *
1.
1"
#78
0.
0"
#79
1$
b101000 *
1.
1"
#80
0.
0"
#81
b101001 *
1.
1"
#82
0/
0.
0"
0,
#83
0+
b101010 *
1.
1"
#84
0.
0"
#85
b101011 *
1.
1"
#86
0.
0"
#87
b101100 *
1.
1"
#88
0.
0"
#89
b101101 *
1.
1"
#90
0.
0"
#91
b101110 *
1.
1"
#92
0.
0"
#93
b101111 *
1.
1"
#94
0.
0"
#95
1+
0$
b110000 *
1/
1.
1"
1,
#96
0.
0"
#97
b110001 *
1.
1"
#98
0.
0"
#99
b110010 *
1.
1"
#100
0.
0"
#101
b110011 *
1.
1"
#102
0.
0"
#103
b110100 *
1.
1"
#104
0.
0"
#105
b110101 *
1.
1"
#106
0.
0"
#107
b110110 *
1.
1"
#108
0.
0"
#109
b110111 *
1.
1"
#110
0.
0"
#111
1$
b111000 *
1.
1"
#112
0.
0"
#113
b111001 *
1.
1"
#114
0.
0"
#115
b111010 *
1.
1"
#116
0.
0"
#117
b111011 *
1.
1"
#118
0.
0"
#119
b111100 *
1.
1"
#120
0.
0"
#121
b111101 *
1.
1"
#122
0/
0.
0"
0,
#123
0+
b111110 *
1.
1"
#124
0.
0"
#125
b111111 *
1.
1"
#126
0.
0"
#127
0$
b1000000 *
1.
1"
#128
0.
0"
#129
b1000001 *
1.
1"
#130
0.
0"
#131
b1000010 *
1.
1"
#132
0.
0"
#133
b1000011 *
1.
1"
#134
0.
0"
#135
b1000100 *
1.
1"
#136
0.
0"
#137
b1000101 *
1.
1"
#138
0.
0"
#139
b1000110 *
1.
1"
#140
0.
0"
#141
b1000111 *
1.
1"
#142
0.
0"
#143
1$
b1001000 *
1.
1"
#144
0.
0"
#145
b1001001 *
1.
1"
#146
0.
0"
#147
b1001010 *
1.
1"
#148
0.
0"
#149
b1001011 *
1.
1"
#150
0.
0"
#151
b1001100 *
1.
1"
