Verilog/CS120A/lab4/testbench.sv
// including design file
`include "design.sv"
`timescale 1ns/1ns;

 module fasystemTest;

    //list of input ports..
    reg clk;
    //add other input ports that you will need. For example the following is for
    //flight attendant system.
    reg Call;
    reg Cancel;
    // add the required input ports for the module you are testing.

    //list of output ports..
    wire Light; //add output ports as required to test your module

    //instantiate your module to be tested here and connect ports appropriately
    //your_module_name uut (.port_name_in_module(port_name_in_testbench),...)
    //As an example module instantiation to test flight attendant call system is given below:

    fasystem_bh uut(.call_button(Call), .cancel_button(Cancel), .light_state(Light), .clk(clk));

    always #1 clk=~clk; // this will create a clock signal with fr equency of(1/2ns=500MZ)

    initial begin

        $dumpfile("fasystemOut.vcd");
        $dumpvars;

        clk=0; //this will initialize clk to logic 0 at time 0ns

        //Start giving stimulation to input ports as required to test your module here.
        //A sample stimulus set to test flight attendant call system
        // is given below as an example:

        Call=0; Cancel=0;
        #17;  //wait for appropriate amount of time so that you can see
        //some impact of input to output (i.e all the clocks in your module at least
        //completes one cycle. This includes the slow_clk as well if used. )
        Call=0; Cancel=1;
        #13;
        Call=1; Cancel=0;
        #19;
        Call=1; Cancel=1;
        #33;
        Call=0; Cancel=1;
        #13;
        Call=1; Cancel=1;
        #27;
        Call=0; Cancel=1;
        #29;

        $finish; //this is very important. Otherwise your test will
        //never stop as clock will keep running infinitely according to line 23.

    end
endmodule

module edgedectectorTest;

    //list of input ports..
    reg clk;
    //add other input ports that you will need. For example the following is for
    //flight attendant system.
    reg signal;
    // add the required input ports for the module you are testing.

    //list of output ports..
    wire outedge; //add output ports as required to test your module

    //instantiate your module to be tested here and connect ports appropriately
    //your_module_name uut (.port_name_in_module(port_name_in_testbench),...)
    //As an example module instantiation to test flight attendant call system is given below:

    edgedetector_bh uut(.clk(clk), .signal(signal), .outedge(outedge));

    always #1 clk=~clk; // this will create a clock signal with fr equency of(1/2ns=500MZ)

    initial begin

        $dumpfile("edgeDetectorOut.vcd");
        $dumpvars;

        clk=0; //this will initialize clk to logic 0 at time 0ns

        //Start giving stimulation to input ports as required to test your module here.
        //A sample stimulus set to test flight attendant call system
        // is given below as an example:

        signal = 0;
        #559;

        signal = 1;
        #559;

        signal = 0;
        #559;

        signal = 1;
        #559;

        signal = 0;
        #559;

        signal = 1;
        #559;

        signal = 0;
        #179;

        signal = 1;
        #99;

        signal = 0;
        #559;

        signal = 1;
        #559;

        signal = 0;
        #559;

        $finish; //this is very important. Otherwise your test will
        //never stop as clock will keep running infinitely according to line 23.

    end
endmodule

Verilog/CS120A/lab4/design.sv
module fasystem_bh(
input wire clk,
input wire call_button ,
input wire cancel_button ,
output reg light_state
);
// Internal wire
reg c_state ;
// Combinatorial block
always @(*) begin
    // q = light_state
    // c_state = call
case ({call_button,cancel_button})
2'b00: c_state = light_state ? 'd1 : 'd0 ;
2'b01: c_state = 'd0 ;

// Write the two following states
2'b10: c_state = 'd1;
2'b11: c_state = 'd1;
default : c_state = 'd0 ;
endcase
end
// Sequential block
always @( posedge clk ) begin
    light_state <= c_state ;
end
endmodule

module edgedetector_bh(
input wire clk,
input wire signal,
output reg outedge );

wire slow_clk ;
reg [1:0] c_state ;
reg [1:0] r_state ;
// Define your FSM states
localparam ZERO = 'd0;
localparam CHANGE = 'd1;
localparam ONE = 'd2;
// EECS150 - Digital Design Lecture 17 - Finite State Machines Revisited
// Code for clkdiv module is given below. Create a new Verilog module in the
//same project with the given code.
clkdiv c1(clk, slow_clk );
// Comb. logic.
always @(*) begin
case (r_state)
ZERO : begin
c_state = signal ? CHANGE : ZERO ;
outedge = 'd0 ;
end
CHANGE : begin
    c_state = signal ? ONE : ZERO ;
    outedge = 'd1;
end
ONE : begin
    c_state = signal ? ONE : ZERO ;
    outedge = 'd0;
end
default : begin
c_state = ZERO ;
outedge = 'd0 ;
end
endcase

end
// Seq. logic
always @( posedge slow_clk ) begin
r_state <= c_state ;
end
endmodule

module clkdiv(clk,clk_out);
input clk;
output clk_out;
reg [15:0] COUNT;
initial COUNT = 0;
assign clk_out=COUNT[3];
always @(posedge clk)
begin
COUNT = COUNT + 1;
end
endmodule

Verilog/CS120A/lab4/fasystemOut.vcd
$date
	Tue May 14 14:07:15 2024
$end
$version
	Icarus Verilog
$end
$timescale
	1ns
$end
$scope module edgedetector_bh $end
$var wire 1 ! clk $end
$var wire 1 " signal $end
$var wire 1 # slow_clk $end
$var parameter 32 $ CHANGE $end
$var parameter 32 % ONE $end
$var parameter 32 & ZERO $end
$var reg 2 ' c_state [1:0] $end
$var reg 1 ( outedge $end
$var reg 2 ) r_state [1:0] $end
$scope module c1 $end
$var wire 1 ! clk $end
$var wire 1 # clk_out $end
$var reg 16 * COUNT [15:0] $end
$upscope $end
$upscope $end
$scope module fasystemTest $end
$var wire 1 + Light $end
$var reg 1 , Call $end
$var reg 1 - Cancel $end
$var reg 1 . clk $end
$scope module uut $end
$var wire 1 , call_button $end
$var wire 1 - cancel_button $end
$var wire 1 . clk $end
$var reg 1 / c_state $end
$var reg 1 + light_state $end
$upscope $end
$upscope $end
$enddefinitions $end
$comment Show the parameter values. $end
$dumpall
b0 &
b10 %
b1 $
$end
#0
$dumpvars
x/
0.
0-
0,
x+
b0 *
bx )
0(
b0 '
0#
z"
z!
$end
#1
1.
#2
0.
#3
1.
#4
0.
#5
1.
#6
0.
#7
1.
#8
0.
#9
1.
#10
0.
#11
1.
#12
0.
#13
1.
#14
0.
#15
1.
#16
0.
#17
0+
0/
1.
1-
#18
0.
#19
1.
#20
0.
#21
1.
#22
0.
#23
1.
#24
0.
#25
1.
#26
0.
#27
1.
#28
0.
#29
1.
#30
1/
0.
0-
1,
#31
1+
1.
#32
0.
#33
1.
#34
0.
#35
1.
#36
0.
#37
1.
#38
0.
#39
1.
#40
0.
#41
1.
#42
0.
#43
1.
#44
0.
#45
1.
#46
0.
#47
1.
#48
0.
#49
1.
1-
#50
0.
#51
1.
#52
0.
#53
1.
#54
0.
#55
1.
#56
0.
#57
1.
#58
0.
#59
1.
#60
0.
#61
1.
#62
0.
#63
1.
#64
0.
#65
1.
#66
0.
#67
1.
#68
0.
#69
1.
#70
0.
#71
1.
#72
0.
#73
1.
#74
0.
#75
1.
#76
0.
#77
1.
#78
0.
#79
1.
#80
0.
#81
1.
#82
0/
0.
0,
#83
0+
1.
#84
0.
#85
1.
#86
0.
#87
1.
#88
0.
#89
1.
#90
0.
#91
1.
#92
0.
#93
1.
#94
0.
#95
1+
1/
1.
1,
#96
0.
#97
1.
#98
0.
#99
1.
#100
0.
#101
1.
#102
0.
#103
1.
#104
0.
#105
1.
#106
0.
#107
1.
#108
0.
#109
1.
#110
0.
#111
1.
#112
0.
#113
1.
#114
0.
#115
1.
#116
0.
#117
1.
#118
0.
#119
1.
#120
0.
#121
1.
#122
0/
0.
0,
#123
0+
1.
