Verilog/CS120A/lab5/design.sv
module falogic(
output r, // We label our output as r instead of z
input x,
input y,
input cin
);
wire t1;
xor cx1 ( t1, x,y );
xor cx2 ( r, t1, cin );
endmodule

module register_logic(
input clk,
input enable ,
input [4:0] Data ,
output reg [4:0] Q ) ;
// on real FPGA board which has clk signal, we use the following always
//statement:
// always @(posedge clk )
// begin
// if ( enable) begin
// Q = Data;
// end
// end
// endmodule
// for simulation, we force the statement to execute without clk signal:
always @(*) begin
if ( enable) begin
Q = Data;
    end
end
endmodule

module carrylogic(
output [3:0] cout ,
input cin,
input [3:0] x,
input [3:0] y
);
// Computing all gx
// if carry out is required
wire g0, g1, g2, g3 ;
assign g0 = x[0] & y[0] ;
assign g1 = x[1] & y[1] ;
assign g2 = x[2] & y[2] ;//Your code ;
assign g3 = x[3] & y[3] ;//Your code ;
// Computing all px
// Addition
wire p0, p1, p2, p3 ;
assign p0 = x[0] | y[0] ; // | is bitwise OR
assign p1 = x[1] | y[1] ;
assign p2 = x[2] | y[2] ;//Your code ;
assign p3 = x[3] | y[3] ;//Your code ;
// Computing all carries outs
assign cout[0] = g0 | ( p0 & cin) ;
assign cout[1] = g1 | ( p1 & ( g0 | ( p0 & cin) ) ) ;
// TODO  (I think this is it)
assign cout[2] = g2 | ( p2 & ( g1 | ( p1 & ( g0 | ( p0 & cin) ) )));
assign cout[3] = g3 | ( p3 & ( g2 | ( p2 & ( g1 | ( p1 & ( g0 | (p0 & cin) ) ))) ));
endmodule

module carrylookahead_st(
input clk ,
input cin,
input [3:0] x,
input [3:0] y,
output cout,
output [3:0] r
);
wire [3:0] c;
wire [3:0] ir1 ;
wire [4:0] ir2 ;
// Compute Carries
carrylogic cx1 ( c, cin, x, y ) ;
// Compute R
falogic cx6 ( ir1[0], x[0], y[0], cin ) ;
// TODO
// Your code (3 more full adders)
falogic cx7 (ir1[1], x[1], y[1], c[0]);
falogic cx8 (ir1[2], x[2], y[2], c[1]);
falogic cx9 (ir1[3], x[3], y[3], c[2]);

// Register
register_logic cx10 ( clk, 1'b1, {c[3],ir1}, ir2 ) ;

// Results
assign r = ir2[3:0] ;
assign cout = ir2[4] ;
endmodule

Verilog/CS120A/lab5/testbench.sv
`timescale 1ns / 1ps
`include "design.sv"


module carrylookahead_tb;
// Inputs
reg cin;
reg [3:0] x;
reg [3:0] y;
reg clk;
// Outputs
wire cout;
wire [3:0] r;
reg [3:0] rx;
integer index ;
//always @(*) // no sensitivity list, so it always executes
// begin
// clk = 1; #100; clk = 0; #100; // 10ns period
// end
// Instantiate the Unit Under Test (UUT)
carrylookahead_st uut (
.clk(clk),
.cin(cin),
.x(x),
.y(y),
.cout(cout),
.r(r)
);

initial begin
$dumpfile("dump.vcd"); $dumpvars;
// Initialize Inputs
cin = 'd0;
y = 'd0;
// r = x + 0 ; cout = 0;
$display("TC11 ");
for (index=0; index < 15; index = index + 1) begin

x = index ;
#100;
if ( r != x ) $display ("Result is wrong");
if ( cout != 1'b0 ) $display ("Result is wrong - Carryout ");
end
// r = x + 1 ;
cin = 1'b1;
y = 4'b0;
$display("TC12 ");
for (index=0; index < 15; index = index + 1) begin

x = index ;
#100;
if ( r != (x + 'd1) ) $display ("Result is wrong %b %b" , r, (x+1) );

if ( cout != 1'b0 ) $display ("Result is wrong - Carryout ");
end
// r = x + y + 1 ;

cin = 1'b1;
$display("TC13 ");
for (index=0; index < 8; index = index + 1) begin

x = index ;
y = index ;
#100;
if ( r != (x + y +1 ) ) $display ("Result is wrong %b %b" , r, (x+y) );

if ( cout != 1'b0 ) $display ("Result is wrong - Carryout ");
end
// r = x + y + 1 ;
cin = 1'b1;
$display("TC14 ");
for (index=8; index < 16; index = index + 1) begin

x = index ;
y = index ;
rx = x + y + cin ;
#100;
if ( r != rx ) $display ("Result is wrong %b %b" , r, rx );

if ( cout != 1'b1 ) $display ("Result is wrong - Carryout ");
end
end
endmodule

Verilog/CS120A/lab5/dump.vcd
$date
	Tue May 28 13:57:29 2024
$end
$version
	Icarus Verilog
$end
$timescale
	1ps
$end
$scope module carrylookahead_tb $end
$var wire 4 ! r [3:0] $end
$var wire 1 " cout $end
$var reg 1 # cin $end
$var reg 1 $ clk $end
$var reg 4 % rx [3:0] $end
$var reg 4 & x [3:0] $end
$var reg 4 ' y [3:0] $end
$var integer 32 ( index [31:0] $end
$scope module uut $end
$var wire 1 # cin $end
$var wire 1 $ clk $end
$var wire 4 ) x [3:0] $end
$var wire 4 * y [3:0] $end
$var wire 4 + r [3:0] $end
$var wire 5 , ir2 [4:0] $end
$var wire 4 - ir1 [3:0] $end
$var wire 1 " cout $end
$var wire 4 . c [3:0] $end
$scope module cx1 $end
$var wire 1 # cin $end
$var wire 1 / g0 $end
$var wire 1 0 g1 $end
$var wire 1 1 g2 $end
$var wire 1 2 g3 $end
$var wire 1 3 p0 $end
$var wire 1 4 p1 $end
$var wire 1 5 p2 $end
$var wire 1 6 p3 $end
$var wire 4 7 x [3:0] $end
$var wire 4 8 y [3:0] $end
$var wire 4 9 cout [3:0] $end
$upscope $end
$scope module cx10 $end
$var wire 5 : Data [4:0] $end
$var wire 1 $ clk $end
$var wire 1 ; enable $end
$var reg 5 < Q [4:0] $end
$upscope $end
$scope module cx6 $end
$var wire 1 # cin $end
$var wire 1 = r $end
$var wire 1 > t1 $end
$var wire 1 ? x $end
$var wire 1 @ y $end
$upscope $end
$scope module cx7 $end
$var wire 1 A cin $end
$var wire 1 B r $end
$var wire 1 C t1 $end
$var wire 1 D x $end
$var wire 1 E y $end
$upscope $end
$scope module cx8 $end
$var wire 1 F cin $end
$var wire 1 G r $end
$var wire 1 H t1 $end
$var wire 1 I x $end
$var wire 1 J y $end
$upscope $end
$scope module cx9 $end
$var wire 1 K cin $end
$var wire 1 L r $end
$var wire 1 M t1 $end
$var wire 1 N x $end
$var wire 1 O y $end
$upscope $end
$upscope $end
$upscope $end
$enddefinitions $end
$comment Show the parameter values. $end
$dumpall
$end
#0
$dumpvars
0O
0N
0M
0L
0K
0J
0I
0H
0G
0F
0E
0D
0C
0B
0A
0@
0?
0>
0=
b0 <
1;
b0 :
b0 9
b0 8
b0 7
06
05
04
03
02
01
00
0/
b0 .
b0 -
b0 ,
b0 +
b0 *
b0 )
b0 (
b0 '
b0 &
bx %
x$
0#
0"
b0 !
$end
#100000
b1 !
b1 +
b1 ,
b1 <
b1 :
b1 -
1=
1>
13
1?
b1 &
b1 )
b1 7
b1 (
#200000
b10 !
b10 +
b10 ,
b10 <
0=
b10 :
b10 -
1B
0>
1C
03
14
0?
1D
b10 &
b10 )
b10 7
b10 (
#300000
b11 !
b11 +
b11 ,
b11 <
b11 :
b11 -
1=
1>
13
1?
b11 &
b11 )
b11 7
b11 (
#400000
b100 !
b100 +
b100 ,
b100 <
0=
0B
b100 :
b100 -
1G
0>
0C
1H
03
04
15
0?
0D
1I
b100 &
b100 )
b100 7
b100 (
#500000
b101 !
b101 +
b101 ,
b101 <
b101 :
b101 -
1=
1>
13
1?
b101 &
b101 )
b101 7
b101 (
#600000
b110 !
b110 +
b110 ,
b110 <
0=
b110 :
b110 -
1B
0>
1C
03
14
0?
1D
b110 &
b110 )
b110 7
b110 (
#700000
b111 !
b111 +
b111 ,
b111 <
b111 :
b111 -
1=
1>
13
1?
b111 &
b111 )
b111 7
b111 (
#800000
b1000 !
b1000 +
b1000 ,
b1000 <
0=
0B
0G
b1000 :
b1000 -
1L
0>
0C
0H
1M
03
04
05
16
0?
0D
0I
1N
b1000 &
b1000 )
b1000 7
b1000 (
#900000
b1001 !
b1001 +
b1001 ,
b1001 <
b1001 :
b1001 -
1=
1>
13
1?
b1001 &
b1001 )
b1001 7
b1001 (
#1000000
b1010 !
b1010 +
b1010 ,
b1010 <
0=
b1010 :
b1010 -
1B
0>
1C
03
14
0?
1D
b1010 &
b1010 )
b1010 7
b1010 (
#1100000
b1011 !
b1011 +
b1011 ,
b1011 <
b1011 :
b1011 -
1=
1>
13
1?
b1011 &
b1011 )
b1011 7
b1011 (
#1200000
b1100 !
b1100 +
b1100 ,
b1100 <
0=
0B
b1100 :
b1100 -
1G
0>
0C
1H
03
04
15
0?
0D
1I
b1100 &
b1100 )
b1100 7
b1100 (
#1300000
b1101 !
b1101 +
b1101 ,
b1101 <
b1101 :
b1101 -
1=
1>
13
1?
b1101 &
b1101 )
b1101 7
b1101 (
#1400000
b1110 !
b1110 +
b1110 ,
b1110 <
0=
b1110 :
b1110 -
1B
0>
1C
03
14
0?
1D
b1110 &
b1110 )
b1110 7
b1110 (
#1500000
0B
0G
0L
b1 !
b1 +
0C
0H
0M
04
05
06
b1 ,
b1 <
0D
0I
0N
b1 :
b1 -
1=
b0 &
b0 )
b0 7
1#
b0 (
#1600000
1B
b10 !
b10 +
1A
b10 ,
b10 <
b1 .
b1 9
b10 :
b10 -
0=
1>
13
1?
b1 &
b1 )
b1 7
b1 (
#1700000
0G
b11 !
b11 +
0A
0F
b11 ,
b11 <
b0 .
b0 9
1=
b11 :
b11 -
1B
0>
1C
03
14
0?
1D
b10 &
b10 )
b10 7
b10 (
#1800000
1G
1F
0B
b100 !
b100 +
1A
b100 ,
b100 <
b11 .
b11 9
b100 :
b100 -
0=
1>
13
1?
b11 &
b11 )
b11 7
b11 (
#1900000
0L
b101 !
b101 +
0A
0F
0K
b101 ,
b101 <
b0 .
b0 9
1=
0B
b101 :
b101 -
1G
0>
0C
1H
03
04
15
0?
0D
1I
b100 &
b100 )
b100 7
b100 (
#2000000
1B
b110 !
b110 +
1A
b110 ,
b110 <
b1 .
b1 9
b110 :
b110 -
0=
1>
13
1?
b101 &
b101 )
b101 7
b101 (
#2100000
0L
0K
1G
b111 !
b111 +
0A
0F
b111 ,
b111 <
b0 .
b0 9
1=
b111 :
b111 -
1B
0>
1C
03
14
0?
1D
b110 &
b110 )
b110 7
b110 (
#2200000
1L
1K
0G
1F
0B
b1000 !
b1000 +
1A
b1000 ,
b1000 <
b111 .
b111 9
b1000 :
b1000 -
0=
1>
13
1?
b111 &
b111 )
b111 7
b111 (
#2300000
0"
b1001 !
b1001 +
0A
0F
0K
b1001 ,
b1001 <
b0 .
b0 9
1=
0B
0G
b1001 :
b1001 -
1L
0>
0C
0H
1M
03
04
05
16
0?
0D
0I
1N
b1000 &
b1000 )
b1000 7
b1000 (
#2400000
1B
b1010 !
b1010 +
1A
b1010 ,
b1010 <
b1 .
b1 9
b1010 :
b1010 -
0=
1>
13
1?
b1001 &
b1001 )
b1001 7
b1001 (
#2500000
0G
b1011 !
b1011 +
0A
0F
b1011 ,
b1011 <
b0 .
b0 9
1=
b1011 :
b1011 -
1B
0>
1C
03
14
0?
1D
b1010 &
b1010 )
b1010 7
b1010 (
#2600000
1G
1F
0B
b1100 !
b1100 +
1A
b1100 ,
b1100 <
b11 .
b11 9
b1100 :
b1100 -
0=
1>
13
1?
b1011 &
b1011 )
b1011 7
b1011 (
#2700000
0"
1L
b1101 !
b1101 +
0A
0F
0K
b1101 ,
b1101 <
b0 .
b0 9
1=
0B
b1101 :
b1101 -
1G
0>
0C
1H
03
04
15
0?
0D
1I
b1100 &
b1100 )
b1100 7
b1100 (
#2800000
1B
b1110 !
b1110 +
1A
b1110 ,
b1110 <
b1 .
b1 9
b1110 :
b1110 -
0=
1>
13
1?
b1101 &
b1101 )
b1101 7
b1101 (
#2900000
0"
1L
0K
1G
b1111 !
b1111 +
0A
0F
b1111 ,
b1111 <
b0 .
b0 9
1=
b1111 :
b1111 -
1B
0>
1C
03
14
0?
1D
b1110 &
b1110 )
b1110 7
b1110 (
#3000000
b1 !
b1 +
b1 ,
b1 <
0B
0G
b1 :
b1 -
0L
0C
0H
0M
04
05
06
0D
0I
0N
b0 &
b0 )
b0 7
b0 (
#3100000
b11 !
b11 +
b11 ,
b11 <
b11 :
b11 -
1B
1A
b1 .
b1 9
1/
13
1@
1?
b1 '
b1 *
b1 8
b1 &
b1 )
b1 7
b1 (
#3200000
b101 !
b101 +
b101 ,
b101 <
0B
b101 :
b101 -
1G
0A
1F
b10 .
b10 9
0/
10
03
14
0@
1E
0?
1D
b10 '
b10 *
b10 8
b10 &
b10 )
b10 7
b10 (
#3300000
b111 !
b111 +
b111 ,
b111 <
b111 :
b111 -
1B
1A
b11 .
b11 9
1/
13
1@
1?
b11 '
b11 *
b11 8
b11 &
b11 )
b11 7
b11 (
#3400000
b1001 !
b1001 +
b1001 ,
b1001 <
0B
0G
b1001 :
b1001 -
1L
0A
0F
1K
b100 .
b100 9
0/
00
11
03
04
15
0@
0E
1J
0?
0D
1I
b100 '
b100 *
b100 8
b100 &
b100 )
b100 7
b100 (
#3500000
b1011 !
b1011 +
b1011 ,
b1011 <
b1011 :
b1011 -
1B
1A
b101 .
b101 9
1/
13
1@
1?
b101 '
b101 *
b101 8
b101 &
b101 )
b101 7
b101 (
#3600000
b1101 !
b1101 +
b1101 ,
b1101 <
0B
b1101 :
b1101 -
1G
0A
1F
b110 .
b110 9
0/
10
03
14
0@
1E
0?
1D
b110 '
b110 *
b110 8
b110 &
b110 )
b110 7
b110 (
#3700000
b1111 !
b1111 +
b1111 ,
b1111 <
b1111 :
b1111 -
1B
1A
b111 .
b111 9
1/
13
1@
1?
b111 '
b111 *
b111 8
b111 &
b111 )
b111 7
b111 (
#3800000
b1 !
b1 +
1"
0B
0G
b1 -
0L
b10001 ,
b10001 <
0A
0F
0K
b10001 :
b1000 .
b1000 9
0/
00
01
12
03
04
05
16
0@
0E
0J
1O
0?
0D
0I
1N
b1 %
b1000 '
b1000 *
b1000 8
b1000 &
b1000 )
b1000 7
b1000 (
#3900000
b11 !
b11 +
b10011 ,
b10011 <
b10011 :
b11 -
1B
1A
b1001 .
b1001 9
1/
13
1@
1?
b11 %
b1001 '
b1001 *
b1001 8
b1001 &
b1001 )
b1001 7
b1001 (
#4000000
b101 !
b101 +
b10101 ,
b10101 <
0B
b10101 :
b101 -
1G
0A
1F
b1010 .
b1010 9
0/
10
03
14
0@
1E
0?
1D
b101 %
b1010 '
b1010 *
b1010 8
b1010 &
b1010 )
b1010 7
b1010 (
#4100000
b111 !
b111 +
b10111 ,
b10111 <
b10111 :
b111 -
1B
1A
b1011 .
b1011 9
1/
13
1@
1?
b111 %
b1011 '
b1011 *
b1011 8
b1011 &
b1011 )
b1011 7
b1011 (
#4200000
b1001 !
b1001 +
b11001 ,
b11001 <
0B
0G
b11001 :
b1001 -
1L
0A
0F
1K
b1100 .
b1100 9
0/
00
11
03
04
15
0@
0E
1J
0?
0D
1I
b1001 %
b1100 '
b1100 *
b1100 8
b1100 &
b1100 )
b1100 7
b1100 (
#4300000
b1011 !
b1011 +
b11011 ,
b11011 <
b11011 :
b1011 -
1B
1A
b1101 .
b1101 9
1/
13
1@
1?
b1011 %
b1101 '
b1101 *
b1101 8
b1101 &
b1101 )
b1101 7
b1101 (
#4400000
b1101 !
b1101 +
b11101 ,
b11101 <
0B
b11101 :
b1101 -
1G
0A
1F
b1110 .
b1110 9
0/
10
03
14
0@
1E
0?
1D
b1101 %
b1110 '
b1110 *
b1110 8
b1110 &
b1110 )
b1110 7
b1110 (
#4500000
b1111 !
b1111 +
b11111 ,
b11111 <
b11111 :
b1111 -
1B
1A
b1111 .
b1111 9
1/
13
1@
1?
b1111 %
b1111 '
b1111 *
b1111 8
b1111 &
b1111 )
b1111 7
b1111 (
#4600000
b10000 (
